zeckendorf/__init__.py
zeckendorf/bwinf_docu_writer.py
zeckendorf/tables.py
zeckendorf-0.1.5.dist-info/LICENSE
zeckendorf-0.1.5.dist-info/METADATA
zeckendorf-0.1.5.dist-info/WHEEL
zeckendorf-0.1.5.dist-info/top_level.txt
zeckendorf-0.1.5.dist-info/RECORD
