Metadata-Version: 2.1
Name: zeckendorf
Version: 0.1.5
Summary: Tools aus purer Gierigkeit.
Author: Zeck
Author-email: synowiecphilip@gmail.com
Classifier: Programming Language :: Python :: 3
Classifier: License :: OSI Approved :: MIT License
Classifier: Operating System :: OS Independent
Requires-Python: >=3.6
License-File: LICENSE
